drishti/__init__.py
drishti/main.py
drishti/snippets/__init__.py
drishti/snippets/hdf5-alignment.c
drishti/snippets/hdf5-cache.c
drishti/snippets/hdf5-collective-metadata.c
drishti/snippets/hdf5-vol-async-read.c
drishti/snippets/hdf5-vol-async-write.c
drishti/snippets/lustre-striping.bash
drishti/snippets/mpi-io-collective-read.c
drishti/snippets/mpi-io-collective-write.c
drishti/snippets/mpi-io-hints.bash
drishti/snippets/mpi-io-iread.c
drishti/snippets/mpi-io-iwrite.c
drishti/snippets/pnetcdf-hdf5-no-fill.c
drishti_io-0.6.dist-info/LICENSE
drishti_io-0.6.dist-info/METADATA
drishti_io-0.6.dist-info/WHEEL
drishti_io-0.6.dist-info/entry_points.txt
drishti_io-0.6.dist-info/top_level.txt
drishti_io-0.6.dist-info/RECORD
