Metadata-Version: 2.1
Name: drishti-io
Version: 0.6
Home-page: https://github.com/hpc-io/drishti
Author: Jean Luca Bez, Suren Byna
Author-email: jlbez@lbl.gov, sbyna@lbl.gov
Keywords: drishti
Classifier: Development Status :: 4 - Beta
Classifier: Environment :: Console
Classifier: Intended Audience :: Developers
Classifier: Intended Audience :: Science/Research
Classifier: License :: Other/Proprietary License
Classifier: Programming Language :: Python :: 3 :: Only
Requires-Python: >=3.6
License-File: LICENSE
Requires-Dist: argparse
Requires-Dist: pandas
Requires-Dist: darshan
Requires-Dist: rich (==12.5.1)
